fmp_wrapper.py
fmp_wrapper-0.1.6.dist-info/METADATA
fmp_wrapper-0.1.6.dist-info/WHEEL
fmp_wrapper-0.1.6.dist-info/top_level.txt
fmp_wrapper-0.1.6.dist-info/RECORD
